README.rst
setup.py
lfsr/__init__.py
lfsr/db.py
lfsr.egg-info/PKG-INFO
lfsr.egg-info/SOURCES.txt
lfsr.egg-info/dependency_links.txt
lfsr.egg-info/top_level.txt
lfsr/../VERSION