Metadata-Version: 1.1
Name: lfsr
Version: 0.1
Summary: Linear Feedback Shift Register toolkit.
Home-page: https://github.com/gergelyk/pylfsr
Author: Grzegorz Krason
Author-email: grzegorz@krason.biz
License: MIT
Download-URL: https://github.com/gergelyk/pylfsr/tarball/0.1
Keywords: lfsr,prng,random,generator
Platform: UNKNOWN
